electionGraphs/__init__.py
electionGraphs/electionGraphs.py
electionGraphs/example.py
electionGraphs-0.3.4.dist-info/LICENSE
electionGraphs-0.3.4.dist-info/METADATA
electionGraphs-0.3.4.dist-info/WHEEL
electionGraphs-0.3.4.dist-info/top_level.txt
electionGraphs-0.3.4.dist-info/RECORD
