Metadata-Version: 2.1
Name: electionGraphs
Version: 0.3.4
Summary: Create graphs for displaying the result of a election based on a csv-inputfile.
Author: ricochan (alpakaFred)
Author-email: <mico.chan@mailbox.org>
Keywords: python,elections,voting,graphs,charts
Classifier: Development Status :: 4 - Beta
Classifier: Programming Language :: Python :: 3
Classifier: License :: OSI Approved :: MIT License
Classifier: Operating System :: OS Independent
License-File: LICENSE
Requires-Dist: pandas
Requires-Dist: plotly
Requires-Dist: kaleido
Requires-Dist: pillow
